{
  "year" : 2011,
  "senateBillNo" : "A1393-2011",
  "billEvents" : [ {
    "eventDate" : 1294203600000,
    "eventText" : "referred to ways and means",
    "billEventId" : "A1393-2011-1294203600000-referred+to+ways+and+means",
    "sobiReferenceList" : [ ],
    "luceneActive" : true,
    "luceneModified" : 0
  } ],
  "votes" : null,
  "sponsor" : {
    "id" : null,
    "position" : null,
    "fullname" : "Ortiz",
    "branch" : null,
    "contactInfo" : null,
    "guid" : null
  },
  "title" : "Exempts from the sales tax meals served to laborers at farm labor camp commissaries",
  "summary" : "Exempts from the sales tax meals served to laborers at farm labor camp commissaries. ",
  "currentCommittee" : null,
  "sameAs" : "S779",
  "lawSection" : "Tax Law",
  "previousVersions" : [ "A2492-2009" ],
  "coSponsors" : [ {
    "id" : null,
    "position" : null,
    "fullname" : "Boyland",
    "branch" : null,
    "contactInfo" : null,
    "guid" : null
  }, {
    "id" : null,
    "position" : null,
    "fullname" : "DenDekker",
    "branch" : null,
    "contactInfo" : null,
    "guid" : null
  } ],
  "pastCommittees" : null,
  "fulltext" : "\n                           S T A T E   O F   N E W   Y O R K\n       ________________________________________________________________________\n\n                                         1393\n\n                              2011-2012 Regular Sessions\n\n                                 I N  A S S E M B L Y\n\n                                      (PREFILED)\n\n                                    January 5, 2011\n                                      ___________\n\n       Introduced  by  M. of A. ORTIZ, BOYLAND, DenDEKKER -- Multi-Sponsored by\n         -- M. of A. COLTON, HEASTIE, HOYT, ROBINSON -- read once and  referred\n         to the Committee on Ways and Means\n\n       AN  ACT  to  amend  the  tax  law, in relation to the sales tax on meals\n         served to laborers at farm labor camp commissaries\n\n         THE PEOPLE OF THE STATE OF NEW YORK, REPRESENTED IN SENATE AND  ASSEM-\n       BLY, DO ENACT AS FOLLOWS:\n\n    1    Section  1.  Paragraph  (ii) of subdivision (d) of section 1105 of the\n    2  tax law is amended by adding a new subparagraph (C) to read as follows:\n    3    (C) MEALS SERVED TO LABORERS OF A FARM LABOR CAMP IN  ANY  FARM  LABOR\n    4  CAMP  COMMISSARY AS DEFINED IN SECTION TWO HUNDRED TWELVE-C OF THE LABOR\n    5  LAW.\n    6    S 2. This act shall take effect immediately.\n\n\n\n\n\n\n        EXPLANATION--Matter in ITALICS (underscored) is new; matter in brackets\n                             [ ] is old law to be omitted.\n                                                                  LBD03397-01-1\n",
  "memo" : null,
  "law" : null,
  "actClause" : "AN ACT to amend the tax law, in relation to the sales tax on meals served to laborers at farm labor camp commissaries ",
  "sortIndex" : -1,
  "latestAmendment" : null,
  "sobiReferenceList" : [ "SOBI.D110107.T145410.TXT", "SOBI.D110110.T164632.TXT" ],
  "luceneActive" : true,
  "luceneModified" : 1294695992388
}