{
  "year" : 2011,
  "senateBillNo" : "A1493-2011",
  "billEvents" : [ {
    "eventDate" : 1294635600000,
    "eventText" : "referred to governmental operations",
    "billEventId" : "A1493-2011-1294635600000-referred+to+governmental+operations",
    "sobiReferenceList" : [ ],
    "luceneActive" : true,
    "luceneModified" : 0
  } ],
  "votes" : null,
  "sponsor" : {
    "id" : null,
    "position" : null,
    "fullname" : "Tedisco",
    "branch" : null,
    "contactInfo" : null,
    "guid" : null
  },
  "title" : "Provides for the recall power of the electors to remove an elective officer",
  "summary" : "Provides for the recall power of the electors to remove an elective officer. ",
  "currentCommittee" : null,
  "sameAs" : null,
  "lawSection" : "Constitution, Concurrent Resolutions to Amend",
  "previousVersions" : [ "AA9085-2009" ],
  "coSponsors" : [ {
    "id" : null,
    "position" : null,
    "fullname" : "Amedore",
    "branch" : null,
    "contactInfo" : null,
    "guid" : null
  } ],
  "pastCommittees" : null,
  "fulltext" : null,
  "memo" : null,
  "law" : null,
  "actClause" : "Concurrent Resolution of the Senate and Assembly proposing the addition of a new article 20 to the constitution, in relation to providing for recall of an elective officer ",
  "sortIndex" : -1,
  "latestAmendment" : null,
  "sobiReferenceList" : [ "SOBI.D110110.T142112.TXT" ],
  "luceneActive" : true,
  "luceneModified" : 1294687272278
}