{
  "year" : 2011,
  "senateBillNo" : "A1507-2011",
  "billEvents" : [ {
    "eventDate" : 1294635600000,
    "eventText" : "referred to ways and means",
    "billEventId" : "A1507-2011-1294635600000-referred+to+ways+and+means",
    "sobiReferenceList" : [ ],
    "luceneActive" : true,
    "luceneModified" : 0
  } ],
  "votes" : null,
  "sponsor" : {
    "id" : null,
    "position" : null,
    "fullname" : "Tedisco",
    "branch" : null,
    "contactInfo" : null,
    "guid" : null
  },
  "title" : "Provides for a personal income tax credit for ten percent of the cost of long term health care insurance premiums",
  "summary" : "Provides taxpayers 55 years of age or over with a personal income tax credit in an amount equal to 10% of the annual premium paid for a long term health care insurance contract. ",
  "currentCommittee" : null,
  "sameAs" : null,
  "lawSection" : "Tax Law",
  "previousVersions" : [ "A10529-2009" ],
  "coSponsors" : null,
  "pastCommittees" : null,
  "fulltext" : "\n                           S T A T E   O F   N E W   Y O R K\n       ________________________________________________________________________\n\n                                         1507\n\n                              2011-2012 Regular Sessions\n\n                                 I N  A S S E M B L Y\n\n                                   January 10, 2011\n                                      ___________\n\n       Introduced by M. of A. TEDISCO -- Multi-Sponsored by -- M. of A. FITZPA-\n         TRICK,  OAKS  --  read  once and referred to the Committee on Ways and\n         Means\n\n       AN ACT to amend the tax law, in relation to authorizing a tax credit for\n         individuals who purchase long term health insurance policies\n\n         THE PEOPLE OF THE STATE OF NEW YORK, REPRESENTED IN SENATE AND  ASSEM-\n       BLY, DO ENACT AS FOLLOWS:\n\n    1    Section  1.  Legislative intent.   The legislature has hitherto recog-\n    2  nized the need to increase the availability of private health  insurance\n    3  for  long term care services provided in residential health care facili-\n    4  ties and community-based settings.   It is the intent  of  this  act  to\n    5  further encourage the development of such plans through the provision of\n    6  tax credits for individuals who purchase state-sanctioned long term care\n    7  health insurance plans.\n    8    S  2. Section 606 of the tax law is amended by adding a new subsection\n    9  (h-1) to read as follows:\n   10    (H-1) CREDIT FOR PURCHASE OF LONG TERM CARE HEALTH INSURANCE.  (1)   A\n   11  TAXPAYER  WHO  IS  FIFTY-FIVE  YEARS  OF AGE OR OLDER SHALL BE ALLOWED A\n   12  CREDIT TO BE CREDITED AGAINST THE TAX IMPOSED  BY  THIS  ARTICLE  IN  AN\n   13  AMOUNT  EQUAL  TO  TEN  PERCENT  OF THE ANNUAL PREMIUM PAID ON AND AFTER\n   14  JANUARY FIRST, TWO THOUSAND ELEVEN FOR A CONTRACT ISSUED  IN  CONNECTION\n   15  WITH  A  HEALTH  INSURANCE  PLAN  FOR  LONG TERM CARE AS PROVIDED FOR IN\n   16  SECTION ONE THOUSAND ONE HUNDRED SEVENTEEN OF THE INSURANCE LAW.\n   17    (2)  IN NO EVENT SHALL THE AMOUNT OF THE CREDIT PROVIDED FOR  IN  THIS\n   18  SUBSECTION  BE  ALLOWED  IN  EXCESS OF THE TAXPAYER'S TAX FOR SUCH YEAR.\n   19  HOWEVER,  IF  THE  AMOUNT  OF  CREDIT  OTHERWISE  ALLOWABLE  UNDER  THIS\n   20  SUBSECTION  FOR  ANY  TAXABLE  YEAR  RESULTS  IN SUCH EXCESS AMOUNT, ANY\n   21  AMOUNT OF CREDIT NOT DEDUCTIBLE IN SUCH TAXABLE YEAR MAY BE CARRIED OVER\n   22  TO THE FOLLOWING YEAR OR YEARS AND MAY BE DEDUCTED FROM  THE  TAXPAYER'S\n   23  TAX FOR SUCH YEAR OR YEARS.\n   24    S 3. This act shall take effect immediately.\n\n        EXPLANATION--Matter in ITALICS (underscored) is new; matter in brackets\n                             [ ] is old law to be omitted.\n                                                                  LBD02051-01-1\n",
  "memo" : null,
  "law" : null,
  "actClause" : "AN ACT to amend the tax law, in relation to authorizing a tax credit for individuals who purchase long term health insurance policies ",
  "sortIndex" : -1,
  "latestAmendment" : null,
  "sobiReferenceList" : [ "SOBI.D110110.T143147.TXT", "SOBI.D110111.T132708.TXT" ],
  "luceneActive" : true,
  "luceneModified" : 1294770428632
}