{
  "year" : 2011,
  "senateBillNo" : "A328-2011",
  "billEvents" : [ {
    "eventDate" : 1294203600000,
    "eventText" : "referred to housing",
    "billEventId" : "A328-2011-1294203600000-referred+to+housing",
    "sobiReferenceList" : [ ],
    "luceneActive" : true,
    "luceneModified" : 0
  } ],
  "votes" : null,
  "sponsor" : {
    "id" : null,
    "position" : null,
    "fullname" : "Montesano",
    "branch" : null,
    "contactInfo" : null,
    "guid" : null
  },
  "title" : "Authorizes municipalities to sell certain municipally owned dwellings to low/moderate income persons for nominal consideration",
  "summary" : "Authorizes municipalities to sell municipally owned 1-4 family residential dwellings requiring rehabilitation to persons of low and moderate income who are first-time homebuyers, for nominal consideration; defines \"persons and families of low and moderate income\" as persons and families who are determined by the municipality to be in the low and moderate income groups and who cannot afford to pay enough to cause private enterprise in the municipality to build a sufficient supply of adequate, safe and sanitary dwellings. ",
  "currentCommittee" : null,
  "sameAs" : null,
  "lawSection" : "Private Housing Finance Law",
  "previousVersions" : [ "A10675-2009" ],
  "coSponsors" : [ {
    "id" : null,
    "position" : null,
    "fullname" : "Molinaro",
    "branch" : null,
    "contactInfo" : null,
    "guid" : null
  }, {
    "id" : null,
    "position" : null,
    "fullname" : "Raia",
    "branch" : null,
    "contactInfo" : null,
    "guid" : null
  }, {
    "id" : null,
    "position" : null,
    "fullname" : "Saladino",
    "branch" : null,
    "contactInfo" : null,
    "guid" : null
  }, {
    "id" : null,
    "position" : null,
    "fullname" : "Castelli",
    "branch" : null,
    "contactInfo" : null,
    "guid" : null
  }, {
    "id" : null,
    "position" : null,
    "fullname" : "Stevenson",
    "branch" : null,
    "contactInfo" : null,
    "guid" : null
  }, {
    "id" : null,
    "position" : null,
    "fullname" : "Rivera N",
    "branch" : null,
    "contactInfo" : null,
    "guid" : null
  } ],
  "pastCommittees" : null,
  "fulltext" : "\n                           S T A T E   O F   N E W   Y O R K\n       ________________________________________________________________________\n\n                                          328\n\n                              2011-2012 Regular Sessions\n\n                                 I N  A S S E M B L Y\n\n                                      (PREFILED)\n\n                                    January 5, 2011\n                                      ___________\n\n       Introduced  by M. of A. MONTESANO, MOLINARO, RAIA, SALADINO -- read once\n         and referred to the Committee on Housing\n\n       AN ACT to amend the private housing finance law, in relation to enacting\n         the state homesteading act\n\n         THE PEOPLE OF THE STATE OF NEW YORK, REPRESENTED IN SENATE AND  ASSEM-\n       BLY, DO ENACT AS FOLLOWS:\n\n    1    Section  1. The private housing finance law is amended by adding a new\n    2  article 8-C to read as follows:\n    3                                ARTICLE VIII-C\n    4                           STATE HOMESTEADING ACT\n    5  SECTION 480. DEFINITIONS.\n    6          481. STATE HOMESTEADING.\n    7    S 480. DEFINITIONS. AS USED IN THIS ARTICLE, THE FOLLOWING TERMS SHALL\n    8  HAVE THE FOLLOWING MEANINGS:\n    9    1. \"PERSONS AND FAMILIES  OF  LOW  AND  MODERATE  INCOME\"  SHALL  MEAN\n   10  PERSONS AND FAMILIES WHO ARE DETERMINED BY THE MUNICIPALITY TO BE IN THE\n   11  LOW  AND  MODERATE  INCOME GROUPS AND WHO CANNOT AFFORD TO PAY ENOUGH TO\n   12  CAUSE PRIVATE ENTERPRISE IN THEIR MUNICIPALITY  TO  BUILD  A  SUFFICIENT\n   13  SUPPLY OF ADEQUATE, SAFE AND SANITARY DWELLINGS.\n   14    2. \"MUNICIPALITY\" SHALL MEAN ANY CITY, TOWN, VILLAGE OR COUNTY.\n   15    3. \"REHABILITATION\" SHALL MEAN REPAIRS, ALTERATIONS OR IMPROVEMENTS OF\n   16  A HOUSING ACCOMMODATION DESIGNED TO RAISE THE HOUSING STANDARDS THEREIN.\n   17    S 481. STATE HOMESTEADING. 1. NOTWITHSTANDING ANY GENERAL, SPECIAL, OR\n   18  LOCAL  LAW, A MUNICIPALITY IS HEREBY AUTHORIZED TO SELL UNOCCUPIED MUNI-\n   19  CIPALLY OWNED ONE- TO FOUR-FAMILY  RESIDENTIAL  DWELLINGS  THAT  REQUIRE\n   20  REHABILITATION  TO  PERSONS AND FAMILIES OF LOW AND MODERATE INCOME, WHO\n   21  ARE FIRST-TIME HOMEBUYERS, FOR NOMINAL CONSIDERATION.\n   22    2. ANY CONTRACT BETWEEN THE MUNICIPALITY  AND  AN  ELIGIBLE  PURCHASER\n   23  MUST  PROVIDE  THAT  ALL CLOSING COSTS BE PAID BY THE PURCHASER AND THAT\n\n        EXPLANATION--Matter in ITALICS (underscored) is new; matter in brackets\n                             [ ] is old law to be omitted.\n                                                                  LBD02307-01-1\n\n       A. 328                              2\n\n    1  THE PURCHASER OCCUPY THE RESIDENTIAL DWELLING WITHIN SIXTY DAYS  OF  THE\n    2  TITLE CLOSING OR OF THE COMPLETION OF THE REPAIR OR REHABILITATION WORK.\n    3    3.  AFTER  THE  CONTRACT HAS BEEN EXECUTED BY THE MUNICIPALITY AND THE\n    4  PURCHASER, THE MUNICIPALITY, IN ITS DISCRETION, MAY PROVIDE THE PURCHAS-\n    5  ER WITH TECHNICAL ASSISTANCE CONCERNING REHABILITATION PLANNING AND HOME\n    6  REPAIR,  FINANCING,  THE  MORTGAGE  APPLICATION  PROCESS,  AND  PROPERTY\n    7  MANAGEMENT. AS PART OF ANY SUCH ASSISTANCE, THE MUNICIPALITY MUST ADVISE\n    8  THE  PURCHASER  AS TO THE AVAILABILITY OF ANY FINANCING DIRECTLY THROUGH\n    9  THE MUNICIPALITY OR THROUGH STATE AND FEDERAL AGENCIES.\n   10    S 2. This act shall take effect immediately.\n",
  "memo" : null,
  "law" : null,
  "actClause" : "AN ACT to amend the private housing finance law, in relation to enacting the state homesteading act ",
  "sortIndex" : -1,
  "latestAmendment" : null,
  "sobiReferenceList" : [ "SOBI.D101220.T110321.TXT", "SOBI.D110125.T142421.TXT", "SOBI.D110125.T091858.TXT", "SOBI.D101221.T103607.TXT", "SOBI.D110119.T144309.TXT" ],
  "luceneActive" : true,
  "luceneModified" : 1295983461607
}