{
  "year" : 2011,
  "senateBillNo" : "S2013-2011",
  "billEvents" : [ {
    "eventDate" : 1294981200000,
    "eventText" : "REFERRED TO LOCAL GOVERNMENT",
    "billEventId" : "S2013-2011-1294981200000-REFERRED+TO+LOCAL+GOVERNMENT",
    "sobiReferenceList" : [ ],
    "luceneActive" : true,
    "luceneModified" : 0
  } ],
  "votes" : null,
  "sponsor" : {
    "id" : null,
    "position" : null,
    "fullname" : "STEWART-COUSINS",
    "branch" : null,
    "contactInfo" : null,
    "guid" : null
  },
  "title" : "Provides for the information technology procurement savings act of 2011; provides local governments and school districts more contracting flexibility",
  "summary" : null,
  "currentCommittee" : "LOCAL GOVERNMENT",
  "sameAs" : null,
  "lawSection" : "General Municipal Law",
  "previousVersions" : null,
  "coSponsors" : [ {
    "id" : null,
    "position" : null,
    "fullname" : "AVELLA",
    "branch" : null,
    "contactInfo" : null,
    "guid" : null
  }, {
    "id" : null,
    "position" : null,
    "fullname" : "KLEIN",
    "branch" : null,
    "contactInfo" : null,
    "guid" : null
  } ],
  "pastCommittees" : null,
  "fulltext" : null,
  "memo" : null,
  "law" : null,
  "actClause" : null,
  "sortIndex" : -1,
  "latestAmendment" : null,
  "sobiReferenceList" : [ "SOBI.D110114.T141447.TXT" ],
  "luceneActive" : true,
  "luceneModified" : 1295032487887
}