{
  "year" : 2011,
  "senateBillNo" : "S2861-2011",
  "billEvents" : [ {
    "eventDate" : 1296622800000,
    "eventText" : "REFERRED TO JUDICIARY",
    "billEventId" : "S2861-2011-1296622800000-REFERRED+TO+JUDICIARY",
    "sobiReferenceList" : [ ],
    "luceneActive" : true,
    "luceneModified" : 0
  } ],
  "votes" : null,
  "sponsor" : {
    "id" : null,
    "position" : null,
    "fullname" : "DEFRANCISCO",
    "branch" : null,
    "contactInfo" : null,
    "guid" : null
  },
  "title" : "Provides that the senate shall be composed of 62 senators, each representing 1 county of the state",
  "summary" : null,
  "currentCommittee" : "JUDICIARY",
  "sameAs" : "A3381",
  "lawSection" : "Constitution, Concurrent Resolutions to Amend",
  "previousVersions" : null,
  "coSponsors" : null,
  "pastCommittees" : null,
  "fulltext" : null,
  "memo" : null,
  "law" : null,
  "actClause" : "Concurrent Resolution of the Senate and Assembly proposing amendments to sections 2 and 4 of article 3 of the constitution, in relation to the number of senators and the apportionment of senate districts ",
  "sortIndex" : -1,
  "latestAmendment" : null,
  "sobiReferenceList" : [ "SOBI.D110202.T121712.TXT", "SOBI.D110202.T115210.TXT", "SOBI.D110202.T115710.TXT" ],
  "luceneActive" : true,
  "luceneModified" : 1296667032832
}